markdown_builder/__init__.py
markdown_builder/document.py
markdown_builder-0.1.2.dist-info/LICENSE
markdown_builder-0.1.2.dist-info/METADATA
markdown_builder-0.1.2.dist-info/WHEEL
markdown_builder-0.1.2.dist-info/top_level.txt
markdown_builder-0.1.2.dist-info/RECORD
