Metadata-Version: 2.1
Name: markdown-builder
Version: 0.1.2
Summary: Create Markdown from a Python program
Home-page: https://github.com/romilly/markdown-builder
Author: Romilly Cocking
Author-email: romilly.cocking@gmail.com
License: UNKNOWN
Project-URL: Bug Tracker, https://github.com/romilly/markdown-builder/issues
Platform: UNKNOWN
Classifier: Programming Language :: Python :: 3
Classifier: License :: OSI Approved :: MIT License
Classifier: Operating System :: OS Independent
Requires-Python: >=3.8
License-File: LICENSE
